autolik/__init__.py
autolik/autodiff.py
autolik/Dual/__init__.py
autolik/Dual/benchmark.py
autolik/distributions/__init__.py
autolik/distributions/univariate.py
autolik/likelihood/__init__.py
autolik/likelihood/loglik.py
autolik/optim/__init__.py
autolik/optim/optimize.py
autolik-0.1.dist-info/LICENSE
autolik-0.1.dist-info/METADATA
autolik-0.1.dist-info/WHEEL
autolik-0.1.dist-info/top_level.txt
autolik-0.1.dist-info/RECORD
