Metadata-Version: 2.1
Name: autolik
Version: 0.1
Summary: Provide the automatic differentiation for Likelihood maximization routine
Home-page: https://github.com/7lang2yan/autolik.git
Author: Langyan Zang
Author-email: langyan.zang@uzh.ch
License: MIT
Keywords: Automatic differentiation,gradients,likelihood,optimization,Python,Scipy
Platform: UNKNOWN
Classifier: Development Status :: 4 - Beta
Classifier: License :: OSI Approved :: MIT License
Classifier: Programming Language :: Python :: 3.9
License-File: LICENSE
Requires-Dist: scipy
